pier_os_clock.py
pier_os_clock-1.0.0.dist-info/licenses/LICENSE
pier_os_clock-1.0.0.dist-info/METADATA
pier_os_clock-1.0.0.dist-info/WHEEL
pier_os_clock-1.0.0.dist-info/entry_points.txt
pier_os_clock-1.0.0.dist-info/top_level.txt
pier_os_clock-1.0.0.dist-info/RECORD
